Metadata-Version: 2.1
Name: PyGRB
Version: 1.0.2
Summary: A GRB light-curve analysis package.
Home-page: https://github.com/JamesPaynter/PyGRB
Author: James Paynter
Author-email: jims.astronomy@gmail.com
License: BSD-3
Platform: UNKNOWN
Classifier: Programming Language :: Python
Classifier: Programming Language :: Python :: 3
Classifier: Programming Language :: Python :: 3.6
Classifier: Programming Language :: Python :: 3.7
Classifier: Programming Language :: Python :: 3.8
Classifier: License :: OSI Approved :: BSD License
Classifier: Operating System :: OS Independent
Requires-Python: >=3.6.0, <3.9
Requires-Dist: numpy (>=1.18.1)
Requires-Dist: scipy (>=1.1.0)
Requires-Dist: matplotlib (>=2.2.3)
Requires-Dist: astropy (>=3.2.3)
Requires-Dist: xlrd (>=1.1.0)
Requires-Dist: prettytable (>=0.7.2)
Requires-Dist: pandas (>=1.0.1)
Requires-Dist: beautifulsoup4 (>=4.9.0)
Requires-Dist: bilby (==0.5.9)
Requires-Dist: nestle (>=0.2.0)
